auto_workflow/__init__.py
auto_workflow/__main__.py
auto_workflow/artifacts.py
auto_workflow/build.py
auto_workflow/cache.py
auto_workflow/cli.py
auto_workflow/config.py
auto_workflow/connectors/__init__.py
auto_workflow/connectors/adls2.py
auto_workflow/connectors/base.py
auto_workflow/connectors/exceptions.py
auto_workflow/connectors/postgres.py
auto_workflow/connectors/registry.py
auto_workflow/connectors/types.py
auto_workflow/connectors/utils.py
auto_workflow/context.py
auto_workflow/dag.py
auto_workflow/env_overrides.py
auto_workflow/events.py
auto_workflow/exceptions.py
auto_workflow/execution.py
auto_workflow/fanout.py
auto_workflow/flow.py
auto_workflow/lifecycle.py
auto_workflow/logging_middleware.py
auto_workflow/metrics_provider.py
auto_workflow/middleware.py
auto_workflow/py.typed
auto_workflow/scheduler.py
auto_workflow/secrets.py
auto_workflow/task.py
auto_workflow/tracing.py
auto_workflow/types.py
auto_workflow/utils.py
auto_workflow-0.1.2.dist-info/METADATA
auto_workflow-0.1.2.dist-info/WHEEL
auto_workflow-0.1.2.dist-info/entry_points.txt
auto_workflow-0.1.2.dist-info/licenses/LICENSE
auto_workflow-0.1.2.dist-info/RECORD
