Metadata-Version: 2.4
Name: auto-workflow
Version: 0.1.2
Summary: A lightweight, developer-first workflow & task orchestration engine for Python.
License: GPL-3.0-or-later
License-File: LICENSE
Author: andreistoica
Author-email: andreilst@yahoo.ro
Requires-Python: >=3.12,<4.0
Classifier: Development Status :: 3 - Alpha
Classifier: Environment :: Console
Classifier: Intended Audience :: Developers
Classifier: License :: OSI Approved :: GNU General Public License v3 or later (GPLv3+)
Classifier: Programming Language :: Python
Classifier: Programming Language :: Python :: 3
Classifier: Programming Language :: Python :: 3.12
Classifier: Programming Language :: Python :: 3.13
Classifier: Programming Language :: Python :: 3.14
Classifier: Programming Language :: Python :: 3 :: Only
Classifier: Topic :: Software Development :: Libraries
Classifier: Topic :: Software Development :: Libraries :: Application Frameworks
Classifier: Typing :: Typed
Provides-Extra: connectors-adls2
Provides-Extra: connectors-all
Provides-Extra: connectors-postgres
Provides-Extra: connectors-sqlalchemy
Requires-Dist: SQLAlchemy (>=2.0.44,<3.0.0) ; extra == "connectors-sqlalchemy" or extra == "connectors-all"
Requires-Dist: azure-identity (>=1.18.0,<2.0.0) ; extra == "connectors-adls2" or extra == "connectors-all"
Requires-Dist: azure-storage-blob (>=12.23.1,<13.0.0) ; extra == "connectors-adls2" or extra == "connectors-all"
Requires-Dist: azure-storage-file-datalake (>=12.15.0,<13.0.0) ; extra == "connectors-adls2" or extra == "connectors-all"
Requires-Dist: cloudpickle (>=3.0.0,<4.0.0)
Requires-Dist: psycopg[binary] (>=3.2.10,<4.0.0) ; extra == "connectors-postgres" or extra == "connectors-all"
Requires-Dist: psycopg_pool (>=3.2.6,<4.0.0) ; extra == "connectors-postgres" or extra == "connectors-all"
Project-URL: Documentation, https://stoiandl.github.io/auto-workflow/
Project-URL: Homepage, https://github.com/stoiandl/auto-workflow
Project-URL: Repository, https://github.com/stoiandl/auto-workflow
